agent/__init__.py
alpha_agent-0.1.0.dist-info/METADATA
alpha_agent-0.1.0.dist-info/WHEEL
alpha_agent-0.1.0.dist-info/top_level.txt
alpha_agent-0.1.0.dist-info/RECORD
