Metadata-Version: 2.1
Name: alpha-agent
Version: 0.1.0
Summary: A simple agent library for query operations
Home-page: https://github.com/xray918/alpha-agent
Author: Ray
Author-email: xie.xinfa@gmail.com
Classifier: Programming Language :: Python :: 3
Classifier: License :: OSI Approved :: MIT License
Classifier: Operating System :: OS Independent
Requires-Python: >=3.6
Requires-Dist: requests>=2.25.1
